{
  "format": "d8-debug-map",
  "version": 1,
  "arch": "z80",
  "addressWidth": 16,
  "endianness": "little",
  "files": {
    "bubble_sort.zax": {
      "segments": [
        {
          "start": 256,
          "end": 264,
          "lstLine": 13,
          "kind": "code",
          "confidence": "high"
        },
        {
          "start": 256,
          "end": 631,
          "lstLine": 0,
          "kind": "unknown",
          "confidence": "low"
        },
        {
          "start": 264,
          "end": 269,
          "lstLine": 15,
          "kind": "code",
          "confidence": "high"
        },
        {
          "start": 269,
          "end": 274,
          "lstLine": 16,
          "kind": "code",
          "confidence": "high"
        },
        {
          "start": 274,
          "end": 278,
          "lstLine": 13,
          "kind": "code",
          "confidence": "high"
        },
        {
          "start": 278,
          "end": 283,
          "lstLine": 19,
          "kind": "code",
          "confidence": "high"
        },
        {
          "start": 283,
          "end": 295,
          "lstLine": 20,
          "kind": "code",
          "confidence": "high"
        },
        {
          "start": 295,
          "end": 298,
          "lstLine": 21,
          "kind": "code",
          "confidence": "high"
        },
        {
          "start": 298,
          "end": 303,
          "lstLine": 23,
          "kind": "code",
          "confidence": "high"
        },
        {
          "start": 303,
          "end": 315,
          "lstLine": 24,
          "kind": "code",
          "confidence": "high"
        },
        {
          "start": 315,
          "end": 318,
          "lstLine": 25,
          "kind": "code",
          "confidence": "high"
        },
        {
          "start": 318,
          "end": 323,
          "lstLine": 27,
          "kind": "code",
          "confidence": "high"
        },
        {
          "start": 323,
          "end": 326,
          "lstLine": 28,
          "kind": "code",
          "confidence": "high"
        },
        {
          "start": 326,
          "end": 338,
          "lstLine": 29,
          "kind": "code",
          "confidence": "high"
        },
        {
          "start": 338,
          "end": 343,
          "lstLine": 31,
          "kind": "code",
          "confidence": "high"
        },
        {
          "start": 343,
          "end": 346,
          "lstLine": 32,
          "kind": "code",
          "confidence": "high"
        },
        {
          "start": 346,
          "end": 358,
          "lstLine": 33,
          "kind": "code",
          "confidence": "high"
        },
        {
          "start": 358,
          "end": 367,
          "lstLine": 13,
          "kind": "code",
          "confidence": "high"
        },
        {
          "start": 367,
          "end": 375,
          "lstLine": 36,
          "kind": "code",
          "confidence": "high"
        },
        {
          "start": 375,
          "end": 380,
          "lstLine": 38,
          "kind": "code",
          "confidence": "high"
        },
        {
          "start": 380,
          "end": 385,
          "lstLine": 39,
          "kind": "code",
          "confidence": "high"
        },
        {
          "start": 385,
          "end": 390,
          "lstLine": 40,
          "kind": "code",
          "confidence": "high"
        },
        {
          "start": 390,
          "end": 395,
          "lstLine": 41,
          "kind": "code",
          "confidence": "high"
        },
        {
          "start": 395,
          "end": 399,
          "lstLine": 36,
          "kind": "code",
          "confidence": "high"
        },
        {
          "start": 399,
          "end": 401,
          "lstLine": 44,
          "kind": "code",
          "confidence": "high"
        },
        {
          "start": 401,
          "end": 402,
          "lstLine": 45,
          "kind": "code",
          "confidence": "high"
        },
        {
          "start": 402,
          "end": 405,
          "lstLine": 46,
          "kind": "code",
          "confidence": "high"
        },
        {
          "start": 405,
          "end": 408,
          "lstLine": 47,
          "kind": "code",
          "confidence": "high"
        },
        {
          "start": 408,
          "end": 411,
          "lstLine": 48,
          "kind": "code",
          "confidence": "high"
        },
        {
          "start": 411,
          "end": 412,
          "lstLine": 49,
          "kind": "code",
          "confidence": "high"
        },
        {
          "start": 412,
          "end": 415,
          "lstLine": 50,
          "kind": "code",
          "confidence": "high"
        },
        {
          "start": 415,
          "end": 418,
          "lstLine": 51,
          "kind": "code",
          "confidence": "high"
        },
        {
          "start": 418,
          "end": 423,
          "lstLine": 54,
          "kind": "code",
          "confidence": "high"
        },
        {
          "start": 423,
          "end": 435,
          "lstLine": 55,
          "kind": "code",
          "confidence": "high"
        },
        {
          "start": 435,
          "end": 438,
          "lstLine": 56,
          "kind": "code",
          "confidence": "high"
        },
        {
          "start": 438,
          "end": 446,
          "lstLine": 58,
          "kind": "code",
          "confidence": "high"
        },
        {
          "start": 446,
          "end": 455,
          "lstLine": 59,
          "kind": "code",
          "confidence": "high"
        },
        {
          "start": 455,
          "end": 460,
          "lstLine": 61,
          "kind": "code",
          "confidence": "high"
        },
        {
          "start": 460,
          "end": 472,
          "lstLine": 62,
          "kind": "code",
          "confidence": "high"
        },
        {
          "start": 472,
          "end": 475,
          "lstLine": 63,
          "kind": "code",
          "confidence": "high"
        },
        {
          "start": 475,
          "end": 478,
          "lstLine": 65,
          "kind": "code",
          "confidence": "high"
        },
        {
          "start": 478,
          "end": 481,
          "lstLine": 66,
          "kind": "code",
          "confidence": "high"
        },
        {
          "start": 481,
          "end": 482,
          "lstLine": 67,
          "kind": "code",
          "confidence": "high"
        },
        {
          "start": 482,
          "end": 485,
          "lstLine": 68,
          "kind": "code",
          "confidence": "high"
        },
        {
          "start": 485,
          "end": 488,
          "lstLine": 69,
          "kind": "code",
          "confidence": "high"
        },
        {
          "start": 488,
          "end": 509,
          "lstLine": 70,
          "kind": "code",
          "confidence": "high"
        },
        {
          "start": 509,
          "end": 518,
          "lstLine": 74,
          "kind": "code",
          "confidence": "high"
        },
        {
          "start": 518,
          "end": 520,
          "lstLine": 76,
          "kind": "code",
          "confidence": "high"
        },
        {
          "start": 520,
          "end": 521,
          "lstLine": 77,
          "kind": "code",
          "confidence": "high"
        },
        {
          "start": 521,
          "end": 524,
          "lstLine": 46,
          "kind": "code",
          "confidence": "high"
        },
        {
          "start": 524,
          "end": 533,
          "lstLine": 36,
          "kind": "code",
          "confidence": "high"
        },
        {
          "start": 533,
          "end": 541,
          "lstLine": 81,
          "kind": "code",
          "confidence": "high"
        },
        {
          "start": 541,
          "end": 546,
          "lstLine": 83,
          "kind": "code",
          "confidence": "high"
        },
        {
          "start": 546,
          "end": 550,
          "lstLine": 81,
          "kind": "code",
          "confidence": "high"
        },
        {
          "start": 550,
          "end": 552,
          "lstLine": 86,
          "kind": "code",
          "confidence": "high"
        },
        {
          "start": 552,
          "end": 555,
          "lstLine": 87,
          "kind": "code",
          "confidence": "high"
        },
        {
          "start": 555,
          "end": 557,
          "lstLine": 89,
          "kind": "code",
          "confidence": "high"
        },
        {
          "start": 557,
          "end": 558,
          "lstLine": 90,
          "kind": "code",
          "confidence": "high"
        },
        {
          "start": 558,
          "end": 561,
          "lstLine": 91,
          "kind": "code",
          "confidence": "high"
        },
        {
          "start": 561,
          "end": 564,
          "lstLine": 92,
          "kind": "code",
          "confidence": "high"
        },
        {
          "start": 564,
          "end": 565,
          "lstLine": 93,
          "kind": "code",
          "confidence": "high"
        },
        {
          "start": 565,
          "end": 568,
          "lstLine": 94,
          "kind": "code",
          "confidence": "high"
        },
        {
          "start": 568,
          "end": 571,
          "lstLine": 95,
          "kind": "code",
          "confidence": "high"
        },
        {
          "start": 571,
          "end": 583,
          "lstLine": 98,
          "kind": "code",
          "confidence": "high"
        },
        {
          "start": 583,
          "end": 592,
          "lstLine": 100,
          "kind": "code",
          "confidence": "high"
        },
        {
          "start": 592,
          "end": 594,
          "lstLine": 102,
          "kind": "code",
          "confidence": "high"
        },
        {
          "start": 594,
          "end": 595,
          "lstLine": 103,
          "kind": "code",
          "confidence": "high"
        },
        {
          "start": 595,
          "end": 598,
          "lstLine": 91,
          "kind": "code",
          "confidence": "high"
        },
        {
          "start": 598,
          "end": 607,
          "lstLine": 81,
          "kind": "code",
          "confidence": "high"
        },
        {
          "start": 607,
          "end": 619,
          "lstLine": 107,
          "kind": "code",
          "confidence": "high"
        },
        {
          "start": 619,
          "end": 622,
          "lstLine": 108,
          "kind": "code",
          "confidence": "high"
        },
        {
          "start": 622,
          "end": 631,
          "lstLine": 107,
          "kind": "code",
          "confidence": "high"
        },
        {
          "start": 32768,
          "end": 32866,
          "lstLine": 0,
          "kind": "unknown",
          "confidence": "low"
        }
      ],
      "symbols": [
        {
          "name": "swap_values",
          "kind": "label",
          "address": 256,
          "line": 13,
          "scope": "global"
        },
        {
          "name": "__zax_epilogue_0",
          "kind": "label",
          "address": 358,
          "line": 13,
          "scope": "local"
        },
        {
          "name": "bubble_pass",
          "kind": "label",
          "address": 367,
          "line": 36,
          "scope": "global"
        },
        {
          "name": "__zax_while_cond_2",
          "kind": "label",
          "address": 402,
          "line": 46,
          "scope": "local"
        },
        {
          "name": "__zax_if_else_4",
          "kind": "label",
          "address": 418,
          "line": 52,
          "scope": "local"
        },
        {
          "name": "__zax_if_else_6",
          "kind": "label",
          "address": 509,
          "line": 72,
          "scope": "local"
        },
        {
          "name": "__zax_if_else_8",
          "kind": "label",
          "address": 509,
          "line": 71,
          "scope": "local"
        },
        {
          "name": "__zax_epilogue_1",
          "kind": "label",
          "address": 524,
          "line": 36,
          "scope": "local"
        },
        {
          "name": "__zax_while_end_3",
          "kind": "label",
          "address": 524,
          "line": 78,
          "scope": "local"
        },
        {
          "name": "bubble_sort",
          "kind": "label",
          "address": 533,
          "line": 81,
          "scope": "global"
        },
        {
          "name": "__zax_while_cond_11",
          "kind": "label",
          "address": 558,
          "line": 91,
          "scope": "local"
        },
        {
          "name": "__zax_if_else_13",
          "kind": "label",
          "address": 571,
          "line": 96,
          "scope": "local"
        },
        {
          "name": "__zax_epilogue_10",
          "kind": "label",
          "address": 598,
          "line": 81,
          "scope": "local"
        },
        {
          "name": "__zax_while_end_12",
          "kind": "label",
          "address": 598,
          "line": 104,
          "scope": "local"
        },
        {
          "name": "main",
          "kind": "label",
          "address": 607,
          "line": 107,
          "scope": "global"
        },
        {
          "name": "__zax_epilogue_15",
          "kind": "label",
          "address": 622,
          "line": 107,
          "scope": "local"
        },
        {
          "name": "values",
          "kind": "data",
          "address": 32768,
          "line": 10,
          "scope": "global"
        },
        {
          "name": "__zax_startup",
          "kind": "label",
          "address": 32776,
          "scope": "global"
        },
        {
          "name": "LastIndex",
          "kind": "constant",
          "value": 7,
          "address": 7,
          "line": 7,
          "scope": "global"
        },
        {
          "name": "ItemCount",
          "kind": "constant",
          "value": 8,
          "address": 8,
          "line": 6,
          "scope": "global"
        }
      ]
    }
  },
  "segments": [
    {
      "start": 256,
      "end": 631
    },
    {
      "start": 32768,
      "end": 32866
    }
  ],
  "fileList": [
    "bubble_sort.zax"
  ],
  "symbols": [
    {
      "name": "swap_values",
      "kind": "label",
      "address": 256,
      "file": "bubble_sort.zax",
      "line": 13,
      "scope": "global"
    },
    {
      "name": "__zax_epilogue_0",
      "kind": "label",
      "address": 358,
      "file": "bubble_sort.zax",
      "line": 13,
      "scope": "local"
    },
    {
      "name": "bubble_pass",
      "kind": "label",
      "address": 367,
      "file": "bubble_sort.zax",
      "line": 36,
      "scope": "global"
    },
    {
      "name": "__zax_while_cond_2",
      "kind": "label",
      "address": 402,
      "file": "bubble_sort.zax",
      "line": 46,
      "scope": "local"
    },
    {
      "name": "__zax_if_else_4",
      "kind": "label",
      "address": 418,
      "file": "bubble_sort.zax",
      "line": 52,
      "scope": "local"
    },
    {
      "name": "__zax_if_else_6",
      "kind": "label",
      "address": 509,
      "file": "bubble_sort.zax",
      "line": 72,
      "scope": "local"
    },
    {
      "name": "__zax_if_else_8",
      "kind": "label",
      "address": 509,
      "file": "bubble_sort.zax",
      "line": 71,
      "scope": "local"
    },
    {
      "name": "__zax_epilogue_1",
      "kind": "label",
      "address": 524,
      "file": "bubble_sort.zax",
      "line": 36,
      "scope": "local"
    },
    {
      "name": "__zax_while_end_3",
      "kind": "label",
      "address": 524,
      "file": "bubble_sort.zax",
      "line": 78,
      "scope": "local"
    },
    {
      "name": "bubble_sort",
      "kind": "label",
      "address": 533,
      "file": "bubble_sort.zax",
      "line": 81,
      "scope": "global"
    },
    {
      "name": "__zax_while_cond_11",
      "kind": "label",
      "address": 558,
      "file": "bubble_sort.zax",
      "line": 91,
      "scope": "local"
    },
    {
      "name": "__zax_if_else_13",
      "kind": "label",
      "address": 571,
      "file": "bubble_sort.zax",
      "line": 96,
      "scope": "local"
    },
    {
      "name": "__zax_epilogue_10",
      "kind": "label",
      "address": 598,
      "file": "bubble_sort.zax",
      "line": 81,
      "scope": "local"
    },
    {
      "name": "__zax_while_end_12",
      "kind": "label",
      "address": 598,
      "file": "bubble_sort.zax",
      "line": 104,
      "scope": "local"
    },
    {
      "name": "main",
      "kind": "label",
      "address": 607,
      "file": "bubble_sort.zax",
      "line": 107,
      "scope": "global"
    },
    {
      "name": "__zax_epilogue_15",
      "kind": "label",
      "address": 622,
      "file": "bubble_sort.zax",
      "line": 107,
      "scope": "local"
    },
    {
      "name": "values",
      "kind": "data",
      "address": 32768,
      "file": "bubble_sort.zax",
      "line": 10,
      "scope": "global"
    },
    {
      "name": "__zax_startup",
      "kind": "label",
      "address": 32776,
      "file": "bubble_sort.zax",
      "scope": "global"
    },
    {
      "name": "LastIndex",
      "kind": "constant",
      "value": 7,
      "address": 7,
      "file": "bubble_sort.zax",
      "line": 7,
      "scope": "global"
    },
    {
      "name": "ItemCount",
      "kind": "constant",
      "value": 8,
      "address": 8,
      "file": "bubble_sort.zax",
      "line": 6,
      "scope": "global"
    }
  ],
  "generator": {
    "tool": "zax",
    "entrySymbol": "__zax_startup",
    "entryAddress": 32776
  }
}
